CHANGELOG.md
LICENSE
MANIFEST.in
README.md
setup.cfg
setup.py
abl/__init__.py
abl.vpath.egg-info/PKG-INFO
abl.vpath.egg-info/SOURCES.txt
abl.vpath.egg-info/dependency_links.txt
abl.vpath.egg-info/entry_points.txt
abl.vpath.egg-info/not-zip-safe
abl.vpath.egg-info/requires.txt
abl.vpath.egg-info/top_level.txt
abl/vpath/__init__.py
abl/vpath/base/__init__.py
abl/vpath/base/exceptions.py
abl/vpath/base/fs.py
abl/vpath/base/localfs.py
abl/vpath/base/memory.py
abl/vpath/base/misc.py
abl/vpath/base/simpleuri.py
abl/vpath/base/uriparse.py
abl/vpath/base/zip.py